libra_client/__init__.py
libra_client/client.py
libra_client/error.py
libra_client/key_factory.py
libra_client/version.py
libra_client/wallet_library.py
libra_client/cli/account_cmds.py
libra_client/cli/color.py
libra_client/cli/command.py
libra_client/cli/dual_command.py
libra_client/cli/ledger_cmds.py
libra_client/cli/main.py
libra_client/cli/transaction_cmds.py
libra_client/cli/wallet_cmds.py
libra_client/shell/__init__.py
libra_client/shell/account_commands.py
libra_client/shell/client_proxy.py
libra_client/shell/dev_commands.py
libra_client/shell/libra_shell.py
libra_client/shell/query_commands.py
libra_client/shell/transfer_commands.py
libra_client_grpc-1.0.0.dist-info/LICENSE
libra_client_grpc-1.0.0.dist-info/METADATA
libra_client_grpc-1.0.0.dist-info/WHEEL
libra_client_grpc-1.0.0.dist-info/entry_points.txt
libra_client_grpc-1.0.0.dist-info/top_level.txt
libra_client_grpc-1.0.0.dist-info/RECORD
