Metadata-Version: 2.1
Name: libra-client-grpc
Version: 1.0.0
Summary: A CLI inteface Libra client and Python API for Libra blockchain.
Home-page: https://github.com/yuan-xy/libra-client-grpc.git
Author: yuan xinyu
Author-email: yuanxinyu.hangzhou@gmail.com
License: UNKNOWN
Platform: UNKNOWN
Classifier: Programming Language :: Python :: 3
Classifier: License :: OSI Approved :: MIT License
Classifier: Operating System :: OS Independent
Requires-Python: >=3.7
Requires-Dist: PyNaCl
Requires-Dist: canoser (==0.8.2)
Requires-Dist: grpcio
Requires-Dist: libra-core (==0.8.7)
Requires-Dist: mnemonic
Requires-Dist: more-itertools
Requires-Dist: protobuf
Requires-Dist: requests
